[
    {
        "id": 0,
        "type": "GO",
        "name": "Start",
        "graphic_path": "textures_and_fonts/textures/monopoly_single_square_empty.png",
        "width": 100,
        "height": 100
    },
    {
        "id": 1,
        "type": "STREET",
        "name": "Swietochlowice",
        "graphic_path": "textures_and_fonts/textures/monopoly_single_square_brown.png",
        "width": 60,
        "height": 100,
        "price": 60,
        "rent_values": [2, 10, 30, 90, 160, 250],
        "house_price": 50,
        "hotel_price": 50,
        "group_members": [3],
        "mortage": 30
    },
    {
        "id": 2,
        "type": "COMUNITY_CHEST",
        "name": "Kasa Spoleczna",
        "graphic_path": "textures_and_fonts/textures/monopoly_single_square_empty.png",
        "width": 60,
        "height": 100
    },
    {
        "id": 3,
        "type": "STREET",
        "name": "Belchatow",
        "graphic_path": "textures_and_fonts/textures/monopoly_single_square_brown.png",
        "width": 60,
        "height": 100,
        "price": 60,
        "rent_values": [4, 20, 60, 180, 320, 450],
        "house_price": 50,
        "hotel_price": 50,
        "group_members": [1],
        "mortage": 30
    },
    {
        "id": 4,
        "type": "TAX",
        "name": "Podatek Dochodowy",
        "graphic_path": "textures_and_fonts/textures/monopoly_single_square_empty.png",
        "width": 60,
        "height": 100,
        "tax_value": 200
    },
    {
        "id": 5,
        "type": "STATION",
        "name": "Dworzec Centralny",
        "graphic_path": "textures_and_fonts/textures/monopoly_single_square_station.png",
        "width": 60,
        "height": 100,
        "price": 200,
        "rent_values": [25, 50, 100, 200],
        "group_members": [15, 25, 35],
        "mortage": 100
    },
    {
        "id": 6,
        "type": "STREET",
        "name": "Warszawa",
        "graphic_path": "textures_and_fonts/textures/monopoly_single_square_lightblue.png",
        "width": 60,
        "height": 100,
        "price": 100,
        "rent_values": [6, 30, 90, 270, 400, 550],
        "house_price": 50,
        "hotel_price": 50,
        "group_members": [8, 9],
        "mortage": 50
    },
    {
        "id": 7,
        "type": "CHANCE",
        "name": "Szansa",
        "graphic_path": "textures_and_fonts/textures/monopoly_single_square_empty.png",
        "width": 60,
        "height": 100
    },
    {
        "id": 8,
        "type": "STREET",
        "name": "Lublin",
        "graphic_path": "textures_and_fonts/textures/monopoly_single_square_lightblue.png",
        "width": 60,
        "height": 100,
        "price": 100,
        "rent_values": [6, 30, 90, 270, 400, 550],
        "house_price": 50,
        "hotel_price": 50,
        "group_members": [6, 9],
        "mortage": 50
    },
    {
        "id": 9,
        "type": "STREET",
        "name": "Katowice",
        "graphic_path": "textures_and_fonts/textures/monopoly_single_square_lightblue.png",
        "width": 60,
        "height": 100,
        "price": 120,
        "rent_values": [8, 40, 100, 300, 450, 600],
        "house_price": 50,
        "hotel_price": 50,
        "group_members": [6, 8],
        "mortage": 60
    },
    {
        "id": 10,
        "type": "JAIL",
        "name": "Wiezienie",
        "graphic_path": "textures_and_fonts/textures/monopoly_single_square_empty.png",
        "width": 100,
        "height": 100
    },
    {
        "id": 11,
        "type": "STREET",
        "name": "Torun",
        "graphic_path": "textures_and_fonts/textures/monopoly_single_square_pink.png",
        "width": 60,
        "height": 100,
        "price": 140,
        "rent_values": [10, 50, 150, 450, 625, 750],
        "house_price": 100,
        "hotel_price": 100,
        "group_members": [13, 14],
        "mortage": 70
    },
    {
        "id": 12,
        "type": "UTILITY",
        "name": "Elektrownia",
        "graphic_path": "textures_and_fonts/textures/monopoly_single_square_electricity.png",
        "width": 60,
        "height": 100,
        "price": 150,
        "rent_multipliers": [4, 10],
        "group_members": [28],
        "mortage": 75
    },
    {
        "id": 13,
        "type": "STREET",
        "name": "Rybnik",
        "graphic_path": "textures_and_fonts/textures/monopoly_single_square_pink.png",
        "width": 60,
        "height": 100,
        "price": 140,
        "rent_values": [10, 50, 150, 450, 625, 750],
        "house_price": 100,
        "hotel_price": 100,
        "group_members": [11, 14],
        "mortage": 70
    },
    {
        "id": 14,
        "type": "STREET",
        "name": "Lodz",
        "graphic_path": "textures_and_fonts/textures/monopoly_single_square_pink.png",
        "width": 60,
        "height": 100,
        "price": 160,
        "rent_values": [12, 60, 500, 700],
        "house_price": 100,
        "hotel_price": 100,
        "group_members": [11, 13],
        "mortage": 80
    },
    {
        "id": 15,
        "type": "STATION",
        "name": "Lotnisko",
        "graphic_path": "textures_and_fonts/textures/monopoly_single_square_station.png",
        "width": 60,
        "height": 100,
        "price": 200,
        "rent_values": [25, 50, 100, 200],
        "group_members": [5, 25, 35],
        "mortage": 100
    },
    {
        "id": 16,
        "type": "STREET",
        "name": "Chojnice",
        "graphic_path": "textures_and_fonts/textures/monopoly_single_square_orange.png",
        "width": 60,
        "height": 100,
        "price": 180,
        "rent_values": [14, 70, 200, 550, 750, 950],
        "house_price": 100,
        "hotel_price": 100,
        "group_members": [18, 19],
        "mortage": 90
    },
    {
        "id": 17,
        "type": "COMUNITY_CHEST",
        "name": "Kasa Spoleczna",
        "graphic_path": "textures_and_fonts/textures/monopoly_single_square_empty.png",
        "width": 60,
        "height": 100
    },
    {
        "id": 18,
        "type": "STREET",
        "name": "Elblag",
        "graphic_path": "textures_and_fonts/textures/monopoly_single_square_orange.png",
        "width": 60,
        "height": 100,
        "price": 180,
        "rent_values": [14, 70, 200, 550, 750, 950],
        "house_price": 100,
        "hotel_price": 100,
        "group_members": [16, 19],
        "mortage": 90
    },
    {
        "id": 19,
        "type": "STREET",
        "name": "Szczecin",
        "graphic_path": "textures_and_fonts/textures/monopoly_single_square_orange.png",
        "width": 60,
        "height": 100,
        "price": 200,
        "rent_values": [16, 80, 220, 600, 800, 1000],
        "house_price": 100,
        "hotel_price": 100,
        "group_members": [16, 18],
        "mortage": 100
    },
    {
        "id": 20,
        "type": "FREE_PARKING",
        "name": "Bezplatny Parking",
        "graphic_path": "textures_and_fonts/textures/monopoly_single_square_empty.png",
        "width": 100,
        "height": 100
    },
    {
        "id": 21,
        "type": "STREET",
        "name": "Zielona Gora",
        "graphic_path": "textures_and_fonts/textures/monopoly_single_square_red.png",
        "width": 60,
        "height": 100,
        "price": 220,
        "rent_values": [18, 90, 250, 700, 875, 1050],
        "house_price": 150,
        "hotel_price": 150,
        "group_members": [23, 24],
        "mortage": 110
    },
    {
        "id": 22,
        "type": "CHANCE",
        "name": "Szansa",
        "graphic_path": "textures_and_fonts/textures/monopoly_single_square_empty.png",
        "width": 60,
        "height": 100
    },
    {
        "id": 23,
        "type": "STREET",
        "name": "Bydgoszcz",
        "graphic_path": "textures_and_fonts/textures/monopoly_single_square_red.png",
        "width": 60,
        "height": 100,
        "price": 220,
        "rent_values": [18, 90, 250, 700, 875, 1050],
        "house_price": 150,
        "hotel_price": 150,
        "group_members": [21, 24],
        "mortage": 110
    },
    {
        "id": 24,
        "type": "STREET",
        "name": "Tarnow",
        "graphic_path": "textures_and_fonts/textures/monopoly_single_square_red.png",
        "width": 60,
        "height": 100,
        "price": 240,
        "rent_values": [20, 100, 300, 750, 925, 1100],
        "house_price": 150,
        "hotel_price": 150,
        "group_members": [21, 23],
        "mortage": 120
    },
    {
        "id": 25,
        "type": "STATION",
        "name": "Dworzec metra",
        "graphic_path": "textures_and_fonts/textures/monopoly_single_square_station.png",
        "width": 60,
        "height": 100,
        "price": 200,
        "rent_values": [25, 50, 100, 200],
        "group_members": [5, 15, 35],
        "mortage": 100
    },
    {
        "id": 26,
        "type": "STREET",
        "name": "Piotrkow Trybunalski",
        "graphic_path": "textures_and_fonts/textures/monopoly_single_square_yellow.png",
        "width": 60,
        "height": 100,
        "price": 260,
        "rent_values": [22, 110, 330, 800, 975, 1150],
        "house_price": 150,
        "hotel_price": 150,
        "group_members": [27, 29],
        "mortage": 130
    },
    {
        "id": 27,
        "type": "STREET",
        "name": "Wroclaw",
        "graphic_path": "textures_and_fonts/textures/monopoly_single_square_yellow.png",
        "width": 60,
        "height": 100,
        "price": 260,
        "rent_values": [22, 110, 330, 800, 975, 1150],
        "house_price": 150,
        "hotel_price": 150,
        "group_members": [26, 29],
        "mortage": 130
    },
    {
        "id": 28,
        "type": "UTILITY",
        "name": "Wodociagi",
        "graphic_path": "textures_and_fonts/textures/monopoly_single_square_water.png",
        "width": 60,
        "height": 100,
        "price": 150,
        "rent_multipliers": [4, 10],
        "group_members": [12],
        "mortage": 75
    },
    {
        "id": 29,
        "type": "STREET",
        "name": "Kalisz",
        "graphic_path": "textures_and_fonts/textures/monopoly_single_square_yellow.png",
        "width": 60,
        "height": 100,
        "price": 280,
        "rent_values": [24, 120, 360, 850, 1025, 1200],
        "house_price": 150,
        "hotel_price": 150,
        "group_members": [26, 27],
        "mortage": 140
    },
    {
        "id": 30,
        "type": "GO_TO_JAIL",
        "name": "Idziesz do wiezienia!",
        "graphic_path": "textures_and_fonts/textures/monopoly_single_square_empty.png",
        "width": 100,
        "height": 100
    },
    {
        "id": 31,
        "type": "STREET",
        "name": "Krakow",
        "graphic_path": "textures_and_fonts/textures/monopoly_single_square_green.png",
        "width": 60,
        "height": 100,
        "price": 300,
        "rent_values": [26, 130, 390, 900, 1100, 1275],
        "house_price": 200,
        "hotel_price": 200,
        "group_members": [32, 33],
        "mortage": 150
    },
    {
        "id": 32,
        "type": "STREET",
        "name": "Gdynia",
        "graphic_path": "textures_and_fonts/textures/monopoly_single_square_green.png",
        "width": 60,
        "height": 100,
        "price": 300,
        "rent_values": [26, 130, 390, 900, 1100, 1275],
        "house_price": 200,
        "hotel_price": 200,
        "group_members": [31, 33],
        "mortage": 150
    },
    {
        "id": 33,
        "type": "COMUNITY_CHEST",
        "name": "Kasa Spoleczna",
        "graphic_path": "textures_and_fonts/textures/monopoly_single_square_empty.png",
        "width": 60,
        "height": 100
    },
    {
        "id": 34,
        "type": "STREET",
        "name": "Poznan",
        "graphic_path": "textures_and_fonts/textures/monopoly_single_square_green.png",
        "width": 60,
        "height": 100,
        "price": 320,
        "rent_values": [28, 150, 450, 1000, 1200, 1400],
        "house_price": 200,
        "hotel_price": 200,
        "group_members": [31, 32],
        "mortage": 160
    },
    {
        "id": 35,
        "type": "STATION",
        "name": "Port Morski",
        "graphic_path": "textures_and_fonts/textures/monopoly_single_square_station.png",
        "width": 60,
        "height": 100,
        "price": 200,
        "rent_values": [25, 50, 100, 200],
        "group_members": [5, 15, 25],
        "mortage": 100
    },
    {
        "id": 36,
        "type": "CHANCE",
        "name": "Szansa",
        "graphic_path": "textures_and_fonts/textures/monopoly_single_square_empty.png",
        "width": 60,
        "height": 100
    },
    {
        "id": 37,
        "type": "STREET",
        "name": "Gorzow",
        "graphic_path": "textures_and_fonts/textures/monopoly_single_square_darkblue.png",
        "width": 60,
        "height": 100,
        "price": 350,
        "rent_values": [35, 175, 500, 1100, 1300, 1500],
        "house_price": 200,
        "hotel_price": 200,
        "group_members": [39],
        "mortage": 175
    },
    {
        "id": 38,
        "type": "TAX",
        "name": "Podatek Dochodowy",
        "graphic_path": "textures_and_fonts/textures/monopoly_single_square_empty.png",
        "width": 60,
        "height": 100,
        "tax_value": 200
    },
    {
        "id": 39,
        "type": "STREET",
        "name": "Bialystok",
        "graphic_path": "textures_and_fonts/textures/monopoly_single_square_darkblue.png",
        "width": 60,
        "height": 100,
        "price": 400,
        "rent_values": [50, 200, 600, 1400, 1700, 2000],
        "house_price": 200,
        "hotel_price": 200,
        "group_members": [37],
        "mortage": 200
    }
]
